select2rocks/__init__.py
select2rocks/fields.py
select2rocks/models.py
select2rocks/settings.py
select2rocks/widgets.py
select2rocks/static/select2rocks/select2rocks.js
select2rocks/templates/select2rocks/ajax_select2.html
django_select2_rocks-0.9.0.dist-info/LICENSE
django_select2_rocks-0.9.0.dist-info/METADATA
django_select2_rocks-0.9.0.dist-info/WHEEL
django_select2_rocks-0.9.0.dist-info/top_level.txt
django_select2_rocks-0.9.0.dist-info/RECORD
